LICENSE.txt
README.md
setup.py
src/repachain/__init__.py
src/repachain.egg-info/PKG-INFO
src/repachain.egg-info/SOURCES.txt
src/repachain.egg-info/dependency_links.txt
src/repachain.egg-info/top_level.txt