Metadata-Version: 2.1
Name: repachain
Version: 1.0.0
Summary: Minimal blockchain
Home-page: https://github.com/dyuri/minchain
Author: Gyuri Horák
Author-email: dyuri@horak.hu
License: MIT
Platform: any
Classifier: Operating System :: OS Independent
Classifier: Programming Language :: Python :: 3
Classifier: Programming Language :: Python :: 3.6
Classifier: Programming Language :: Python :: 3.7
Classifier: License :: OSI Approved :: MIT License
Requires-Python: >=3.6
